[{"code": "Color 6.6.6 9", "n_k_d": [61, 1, 9], "time_steps": 1, "error_model": "Biased-depolarizing (bias=1, axis='Z')", "decoder": "Color 6.6.6 MPS (chi=36)", "error_probability": 0.14, "measurement_error_probability": 0.0, "n_run": 200, "n_success": 190, "n_fail": 10, "n_logical_commutations": [4, 6], "custom_totals": null, "error_weight_total": 1611, "error_weight_pvar": 7.441975, "logical_failure_rate": 0.05, "physical_error_rate": 0.13204918032786886, "wall_time": 132.99980689398944}, {"code": "Color 6.6.6 9", "n_k_d": [61, 1, 9], "time_steps": 1, "error_model": "Biased-depolarizing (bias=1, axis='Z')", "decoder": "Color 6.6.6 MPS (chi=36)", "error_probability": 0.1511111111111111, "measurement_error_probability": 0.0, "n_run": 200, "n_success": 173, "n_fail": 27, "n_logical_commutations": [19, 11], "custom_totals": null, "error_weight_total": 1819, "error_weight_pvar": 8.575975, "logical_failure_rate": 0.135, "physical_error_rate": 0.1490983606557377, "wall_time": 133.9857232971117}, {"code": "Color 6.6.6 9", "n_k_d": [61, 1, 9], "time_steps": 1, "error_model": "Biased-depolarizing (bias=1, axis='Z')", "decoder": "Color 6.6.6 MPS (chi=36)", "error_probability": 0.16222222222222224, "measurement_error_probability": 0.0, "n_run": 200, "n_success": 170, "n_fail": 30, "n_logical_commutations": [15, 23], "custom_totals": null, "error_weight_total": 1950, "error_weight_pvar": 7.2975, "logical_failure_rate": 0.15, "physical_error_rate": 0.1598360655737705, "wall_time": 134.08158542774618}, {"code": "Color 6.6.6 9", "n_k_d": [61, 1, 9], "time_steps": 1, "error_model": "Biased-depolarizing (bias=1, axis='Z')", "decoder": "Color 6.6.6 MPS (chi=36)", "error_probability": 0.17333333333333334, "measurement_error_probability": 0.0, "n_run": 200, "n_success": 153, "n_fail": 47, "n_logical_commutations": [26, 29], "custom_totals": null, "error_weight_total": 2168, "error_weight_pvar": 8.1444, "logical_failure_rate": 0.235, "physical_error_rate": 0.17770491803278687, "wall_time": 135.8671987215057}, {"code": "Color 6.6.6 9", "n_k_d": [61, 1, 9], "time_steps": 1, "error_model": "Biased-depolarizing (bias=1, axis='Z')", "decoder": "Color 6.6.6 MPS (chi=36)", "error_probability": 0.18444444444444444, "measurement_error_probability": 0.0, "n_run": 200, "n_success": 148, "n_fail": 52, "n_logical_commutations": [32, 32], "custom_totals": null, "error_weight_total": 2234, "error_weight_pvar": 7.4711, "logical_failure_rate": 0.26, "physical_error_rate": 0.18311475409836067, "wall_time": 134.00421806517988}, {"code": "Color 6.6.6 9", "n_k_d": [61, 1, 9], "time_steps": 1, "error_model": "Biased-depolarizing (bias=1, axis='Z')", "decoder": "Color 6.6.6 MPS (chi=36)", "error_probability": 0.19555555555555554, "measurement_error_probability": 0.0, "n_run": 200, "n_success": 141, "n_fail": 59, "n_logical_commutations": [39, 34], "custom_totals": null, "error_weight_total": 2361, "error_weight_pvar": 10.026975, "logical_failure_rate": 0.295, "physical_error_rate": 0.19352459016393442, "wall_time": 134.55114339664578}, {"code": "Color 6.6.6 9", "n_k_d": [61, 1, 9], "time_steps": 1, "error_model": "Biased-depolarizing (bias=1, axis='Z')", "decoder": "Color 6.6.6 MPS (chi=36)", "error_probability": 0.20666666666666667, "measurement_error_probability": 0.0, "n_run": 200, "n_success": 144, "n_fail": 56, "n_logical_commutations": [33, 35], "custom_totals": null, "error_weight_total": 2515, "error_weight_pvar": 9.504375, "logical_failure_rate": 0.28, "physical_error_rate": 0.20614754098360655, "wall_time": 134.97671753168106}, {"code": "Color 6.6.6 9", "n_k_d": [61, 1, 9], "time_steps": 1, "error_model": "Biased-depolarizing (bias=1, axis='Z')", "decoder": "Color 6.6.6 MPS (chi=36)", "error_probability": 0.21777777777777776, "measurement_error_probability": 0.0, "n_run": 200, "n_success": 129, "n_fail": 71, "n_logical_commutations": [49, 38], "custom_totals": null, "error_weight_total": 2650, "error_weight_pvar": 10.2675, "logical_failure_rate": 0.355, "physical_error_rate": 0.21721311475409838, "wall_time": 133.73218210227787}, {"code": "Color 6.6.6 9", "n_k_d": [61, 1, 9], "time_steps": 1, "error_model": "Biased-depolarizing (bias=1, axis='Z')", "decoder": "Color 6.6.6 MPS (chi=36)", "error_probability": 0.22888888888888886, "measurement_error_probability": 0.0, "n_run": 200, "n_success": 113, "n_fail": 87, "n_logical_commutations": [51, 53], "custom_totals": null, "error_weight_total": 2835, "error_weight_pvar": 12.504375, "logical_failure_rate": 0.435, "physical_error_rate": 0.23237704918032787, "wall_time": 132.80647889431566}, {"code": "Color 6.6.6 9", "n_k_d": [61, 1, 9], "time_steps": 1, "error_model": "Biased-depolarizing (bias=1, axis='Z')", "decoder": "Color 6.6.6 MPS (chi=36)", "error_probability": 0.24, "measurement_error_probability": 0.0, "n_run": 200, "n_success": 113, "n_fail": 87, "n_logical_commutations": [62, 46], "custom_totals": null, "error_weight_total": 2875, "error_weight_pvar": 9.034375, "logical_failure_rate": 0.435, "physical_error_rate": 0.23565573770491802, "wall_time": 134.46058902237564}, {"code": "Color 6.6.6 11", "n_k_d": [91, 1, 11], "time_steps": 1, "error_model": "Biased-depolarizing (bias=1, axis='Z')", "decoder": "Color 6.6.6 MPS (chi=36)", "error_probability": 0.14, "measurement_error_probability": 0.0, "n_run": 200, "n_success": 185, "n_fail": 15, "n_logical_commutations": [10, 9], "custom_totals": null, "error_weight_total": 2519, "error_weight_pvar": 11.400975, "logical_failure_rate": 0.075, "physical_error_rate": 0.13840659340659342, "wall_time": 451.7644878802821}, {"code": "Color 6.6.6 11", "n_k_d": [91, 1, 11], "time_steps": 1, "error_model": "Biased-depolarizing (bias=1, axis='Z')", "decoder": "Color 6.6.6 MPS (chi=36)", "error_probability": 0.1511111111111111, "measurement_error_probability": 0.0, "n_run": 200, "n_success": 178, "n_fail": 22, "n_logical_commutations": [10, 13], "custom_totals": null, "error_weight_total": 2774, "error_weight_pvar": 11.2431, "logical_failure_rate": 0.11, "physical_error_rate": 0.1524175824175824, "wall_time": 446.0909465830773}, {"code": "Color 6.6.6 11", "n_k_d": [91, 1, 11], "time_steps": 1, "error_model": "Biased-depolarizing (bias=1, axis='Z')", "decoder": "Color 6.6.6 MPS (chi=36)", "error_probability": 0.16222222222222224, "measurement_error_probability": 0.0, "n_run": 200, "n_success": 171, "n_fail": 29, "n_logical_commutations": [16, 17], "custom_totals": null, "error_weight_total": 2940, "error_weight_pvar": 12.19, "logical_failure_rate": 0.145, "physical_error_rate": 0.16153846153846152, "wall_time": 448.08727234136313}, {"code": "Color 6.6.6 11", "n_k_d": [91, 1, 11], "time_steps": 1, "error_model": "Biased-depolarizing (bias=1, axis='Z')", "decoder": "Color 6.6.6 MPS (chi=36)", "error_probability": 0.17333333333333334, "measurement_error_probability": 0.0, "n_run": 200, "n_success": 158, "n_fail": 42, "n_logical_commutations": [23, 28], "custom_totals": null, "error_weight_total": 3200, "error_weight_pvar": 12.32, "logical_failure_rate": 0.21, "physical_error_rate": 0.17582417582417584, "wall_time": 450.4168249089271}, {"code": "Color 6.6.6 11", "n_k_d": [91, 1, 11], "time_steps": 1, "error_model": "Biased-depolarizing (bias=1, axis='Z')", "decoder": "Color 6.6.6 MPS (chi=36)", "error_probability": 0.18444444444444444, "measurement_error_probability": 0.0, "n_run": 200, "n_success": 152, "n_fail": 48, "n_logical_commutations": [29, 25], "custom_totals": null, "error_weight_total": 3413, "error_weight_pvar": 12.570775, "logical_failure_rate": 0.24, "physical_error_rate": 0.1875274725274725, "wall_time": 447.5915444213897}, {"code": "Color 6.6.6 11", "n_k_d": [91, 1, 11], "time_steps": 1, "error_model": "Biased-depolarizing (bias=1, axis='Z')", "decoder": "Color 6.6.6 MPS (chi=36)", "error_probability": 0.19555555555555554, "measurement_error_probability": 0.0, "n_run": 200, "n_success": 146, "n_fail": 54, "n_logical_commutations": [38, 31], "custom_totals": null, "error_weight_total": 3543, "error_weight_pvar": 11.833775, "logical_failure_rate": 0.27, "physical_error_rate": 0.19467032967032968, "wall_time": 451.1593270152807}, {"code": "Color 6.6.6 11", "n_k_d": [91, 1, 11], "time_steps": 1, "error_model": "Biased-depolarizing (bias=1, axis='Z')", "decoder": "Color 6.6.6 MPS (chi=36)", "error_probability": 0.20666666666666667, "measurement_error_probability": 0.0, "n_run": 200, "n_success": 126, "n_fail": 74, "n_logical_commutations": [44, 48], "custom_totals": null, "error_weight_total": 3743, "error_weight_pvar": 16.673775, "logical_failure_rate": 0.37, "physical_error_rate": 0.20565934065934066, "wall_time": 451.8838858678937}, {"code": "Color 6.6.6 11", "n_k_d": [91, 1, 11], "time_steps": 1, "error_model": "Biased-depolarizing (bias=1, axis='Z')", "decoder": "Color 6.6.6 MPS (chi=36)", "error_probability": 0.21777777777777776, "measurement_error_probability": 0.0, "n_run": 200, "n_success": 104, "n_fail": 96, "n_logical_commutations": [59, 61], "custom_totals": null, "error_weight_total": 4064, "error_weight_pvar": 14.3276, "logical_failure_rate": 0.48, "physical_error_rate": 0.22329670329670329, "wall_time": 452.3366006212309}, {"code": "Color 6.6.6 11", "n_k_d": [91, 1, 11], "time_steps": 1, "error_model": "Biased-depolarizing (bias=1, axis='Z')", "decoder": "Color 6.6.6 MPS (chi=36)", "error_probability": 0.22888888888888886, "measurement_error_probability": 0.0, "n_run": 200, "n_success": 100, "n_fail": 100, "n_logical_commutations": [64, 59], "custom_totals": null, "error_weight_total": 4207, "error_weight_pvar": 15.793775, "logical_failure_rate": 0.5, "physical_error_rate": 0.23115384615384615, "wall_time": 452.47512859478593}, {"code": "Color 6.6.6 11", "n_k_d": [91, 1, 11], "time_steps": 1, "error_model": "Biased-depolarizing (bias=1, axis='Z')", "decoder": "Color 6.6.6 MPS (chi=36)", "error_probability": 0.24, "measurement_error_probability": 0.0, "n_run": 200, "n_success": 100, "n_fail": 100, "n_logical_commutations": [65, 55], "custom_totals": null, "error_weight_total": 4335, "error_weight_pvar": 15.619375, "logical_failure_rate": 0.5, "physical_error_rate": 0.23818681318681317, "wall_time": 452.9160415502265}, {"code": "Color 6.6.6 13", "n_k_d": [127, 1, 13], "time_steps": 1, "error_model": "Biased-depolarizing (bias=1, axis='Z')", "decoder": "Color 6.6.6 MPS (chi=36)", "error_probability": 0.14, "measurement_error_probability": 0.0, "n_run": 200, "n_success": 187, "n_fail": 13, "n_logical_commutations": [9, 8], "custom_totals": null, "error_weight_total": 3512, "error_weight_pvar": 14.2164, "logical_failure_rate": 0.065, "physical_error_rate": 0.13826771653543307, "wall_time": 965.2946004634723}, {"code": "Color 6.6.6 13", "n_k_d": [127, 1, 13], "time_steps": 1, "error_model": "Biased-depolarizing (bias=1, axis='Z')", "decoder": "Color 6.6.6 MPS (chi=36)", "error_probability": 0.1511111111111111, "measurement_error_probability": 0.0, "n_run": 200, "n_success": 182, "n_fail": 18, "n_logical_commutations": [10, 11], "custom_totals": null, "error_weight_total": 3879, "error_weight_pvar": 15.308975, "logical_failure_rate": 0.09, "physical_error_rate": 0.15271653543307087, "wall_time": 966.2293132655323}, {"code": "Color 6.6.6 13", "n_k_d": [127, 1, 13], "time_steps": 1, "error_model": "Biased-depolarizing (bias=1, axis='Z')", "decoder": "Color 6.6.6 MPS (chi=36)", "error_probability": 0.16222222222222224, "measurement_error_probability": 0.0, "n_run": 200, "n_success": 172, "n_fail": 28, "n_logical_commutations": [15, 18], "custom_totals": null, "error_weight_total": 4152, "error_weight_pvar": 16.2824, "logical_failure_rate": 0.14, "physical_error_rate": 0.16346456692913386, "wall_time": 965.3881431501359}, {"code": "Color 6.6.6 13", "n_k_d": [127, 1, 13], "time_steps": 1, "error_model": "Biased-depolarizing (bias=1, axis='Z')", "decoder": "Color 6.6.6 MPS (chi=36)", "error_probability": 0.17333333333333334, "measurement_error_probability": 0.0, "n_run": 200, "n_success": 159, "n_fail": 41, "n_logical_commutations": [27, 26], "custom_totals": null, "error_weight_total": 4332, "error_weight_pvar": 19.4644, "logical_failure_rate": 0.205, "physical_error_rate": 0.17055118110236223, "wall_time": 969.3740343060344}, {"code": "Color 6.6.6 13", "n_k_d": [127, 1, 13], "time_steps": 1, "error_model": "Biased-depolarizing (bias=1, axis='Z')", "decoder": "Color 6.6.6 MPS (chi=36)", "error_probability": 0.18444444444444444, "measurement_error_probability": 0.0, "n_run": 200, "n_success": 141, "n_fail": 59, "n_logical_commutations": [27, 41], "custom_totals": null, "error_weight_total": 4666, "error_weight_pvar": 16.5111, "logical_failure_rate": 0.295, "physical_error_rate": 0.1837007874015748, "wall_time": 968.466345384717}, {"code": "Color 6.6.6 13", "n_k_d": [127, 1, 13], "time_steps": 1, "error_model": "Biased-depolarizing (bias=1, axis='Z')", "decoder": "Color 6.6.6 MPS (chi=36)", "error_probability": 0.19555555555555554, "measurement_error_probability": 0.0, "n_run": 200, "n_success": 136, "n_fail": 64, "n_logical_commutations": [30, 43], "custom_totals": null, "error_weight_total": 4968, "error_weight_pvar": 17.1544, "logical_failure_rate": 0.32, "physical_error_rate": 0.19559055118110236, "wall_time": 972.3357071792707}, {"code": "Color 6.6.6 13", "n_k_d": [127, 1, 13], "time_steps": 1, "error_model": "Biased-depolarizing (bias=1, axis='Z')", "decoder": "Color 6.6.6 MPS (chi=36)", "error_probability": 0.20666666666666667, "measurement_error_probability": 0.0, "n_run": 200, "n_success": 136, "n_fail": 64, "n_logical_commutations": [39, 42], "custom_totals": null, "error_weight_total": 5257, "error_weight_pvar": 23.723775, "logical_failure_rate": 0.32, "physical_error_rate": 0.20696850393700789, "wall_time": 976.1570939924568}, {"code": "Color 6.6.6 13", "n_k_d": [127, 1, 13], "time_steps": 1, "error_model": "Biased-depolarizing (bias=1, axis='Z')", "decoder": "Color 6.6.6 MPS (chi=36)", "error_probability": 0.21777777777777776, "measurement_error_probability": 0.0, "n_run": 200, "n_success": 104, "n_fail": 96, "n_logical_commutations": [57, 63], "custom_totals": null, "error_weight_total": 5572, "error_weight_pvar": 23.0504, "logical_failure_rate": 0.48, "physical_error_rate": 0.2193700787401575, "wall_time": 975.0878856228665}, {"code": "Color 6.6.6 13", "n_k_d": [127, 1, 13], "time_steps": 1, "error_model": "Biased-depolarizing (bias=1, axis='Z')", "decoder": "Color 6.6.6 MPS (chi=36)", "error_probability": 0.22888888888888886, "measurement_error_probability": 0.0, "n_run": 200, "n_success": 95, "n_fail": 105, "n_logical_commutations": [63, 72], "custom_totals": null, "error_weight_total": 5925, "error_weight_pvar": 23.024375, "logical_failure_rate": 0.525, "physical_error_rate": 0.23326771653543307, "wall_time": 976.2534181429073}, {"code": "Color 6.6.6 13", "n_k_d": [127, 1, 13], "time_steps": 1, "error_model": "Biased-depolarizing (bias=1, axis='Z')", "decoder": "Color 6.6.6 MPS (chi=36)", "error_probability": 0.24, "measurement_error_probability": 0.0, "n_run": 200, "n_success": 94, "n_fail": 106, "n_logical_commutations": [72, 63], "custom_totals": null, "error_weight_total": 5978, "error_weight_pvar": 33.1079, "logical_failure_rate": 0.53, "physical_error_rate": 0.2353543307086614, "wall_time": 976.7973224176094}, {"code": "Color 6.6.6 15", "n_k_d": [169, 1, 15], "time_steps": 1, "error_model": "Biased-depolarizing (bias=1, axis='Z')", "decoder": "Color 6.6.6 MPS (chi=36)", "error_probability": 0.14, "measurement_error_probability": 0.0, "n_run": 200, "n_success": 182, "n_fail": 18, "n_logical_commutations": [9, 11], "custom_totals": null, "error_weight_total": 4815, "error_weight_pvar": 19.659375, "logical_failure_rate": 0.09, "physical_error_rate": 0.14245562130177514, "wall_time": 1688.7128671882674}, {"code": "Color 6.6.6 15", "n_k_d": [169, 1, 15], "time_steps": 1, "error_model": "Biased-depolarizing (bias=1, axis='Z')", "decoder": "Color 6.6.6 MPS (chi=36)", "error_probability": 0.1511111111111111, "measurement_error_probability": 0.0, "n_run": 200, "n_success": 186, "n_fail": 14, "n_logical_commutations": [11, 5], "custom_totals": null, "error_weight_total": 5228, "error_weight_pvar": 19.7304, "logical_failure_rate": 0.07, "physical_error_rate": 0.15467455621301776, "wall_time": 1690.3987183924764}, {"code": "Color 6.6.6 15", "n_k_d": [169, 1, 15], "time_steps": 1, "error_model": "Biased-depolarizing (bias=1, axis='Z')", "decoder": "Color 6.6.6 MPS (chi=36)", "error_probability": 0.16222222222222224, "measurement_error_probability": 0.0, "n_run": 200, "n_success": 182, "n_fail": 18, "n_logical_commutations": [12, 9], "custom_totals": null, "error_weight_total": 5569, "error_weight_pvar": 22.650975, "logical_failure_rate": 0.09, "physical_error_rate": 0.16476331360946744, "wall_time": 1688.2270808089525}, {"code": "Color 6.6.6 15", "n_k_d": [169, 1, 15], "time_steps": 1, "error_model": "Biased-depolarizing (bias=1, axis='Z')", "decoder": "Color 6.6.6 MPS (chi=36)", "error_probability": 0.17333333333333334, "measurement_error_probability": 0.0, "n_run": 200, "n_success": 167, "n_fail": 33, "n_logical_commutations": [20, 21], "custom_totals": null, "error_weight_total": 5766, "error_weight_pvar": 27.0811, "logical_failure_rate": 0.165, "physical_error_rate": 0.17059171597633135, "wall_time": 1695.0499672703445}, {"code": "Color 6.6.6 15", "n_k_d": [169, 1, 15], "time_steps": 1, "error_model": "Biased-depolarizing (bias=1, axis='Z')", "decoder": "Color 6.6.6 MPS (chi=36)", "error_probability": 0.18444444444444444, "measurement_error_probability": 0.0, "n_run": 200, "n_success": 152, "n_fail": 48, "n_logical_commutations": [35, 27], "custom_totals": null, "error_weight_total": 6119, "error_weight_pvar": 22.370975, "logical_failure_rate": 0.24, "physical_error_rate": 0.1810355029585799, "wall_time": 1693.420100950636}, {"code": "Color 6.6.6 15", "n_k_d": [169, 1, 15], "time_steps": 1, "error_model": "Biased-depolarizing (bias=1, axis='Z')", "decoder": "Color 6.6.6 MPS (chi=36)", "error_probability": 0.19555555555555554, "measurement_error_probability": 0.0, "n_run": 200, "n_success": 128, "n_fail": 72, "n_logical_commutations": [40, 42], "custom_totals": null, "error_weight_total": 6690, "error_weight_pvar": 31.6075, "logical_failure_rate": 0.36, "physical_error_rate": 0.19792899408284023, "wall_time": 1699.1175155965611}, {"code": "Color 6.6.6 15", "n_k_d": [169, 1, 15], "time_steps": 1, "error_model": "Biased-depolarizing (bias=1, axis='Z')", "decoder": "Color 6.6.6 MPS (chi=36)", "error_probability": 0.20666666666666667, "measurement_error_probability": 0.0, "n_run": 200, "n_success": 132, "n_fail": 68, "n_logical_commutations": [48, 37], "custom_totals": null, "error_weight_total": 6983, "error_weight_pvar": 25.057775, "logical_failure_rate": 0.34, "physical_error_rate": 0.20659763313609467, "wall_time": 1705.1086625307798}, {"code": "Color 6.6.6 15", "n_k_d": [169, 1, 15], "time_steps": 1, "error_model": "Biased-depolarizing (bias=1, axis='Z')", "decoder": "Color 6.6.6 MPS (chi=36)", "error_probability": 0.21777777777777776, "measurement_error_probability": 0.0, "n_run": 200, "n_success": 104, "n_fail": 96, "n_logical_commutations": [66, 54], "custom_totals": null, "error_weight_total": 7470, "error_weight_pvar": 33.0775, "logical_failure_rate": 0.48, "physical_error_rate": 0.2210059171597633, "wall_time": 1711.6773667233065}, {"code": "Color 6.6.6 15", "n_k_d": [169, 1, 15], "time_steps": 1, "error_model": "Biased-depolarizing (bias=1, axis='Z')", "decoder": "Color 6.6.6 MPS (chi=36)", "error_probability": 0.22888888888888886, "measurement_error_probability": 0.0, "n_run": 200, "n_success": 98, "n_fail": 102, "n_logical_commutations": [61, 56], "custom_totals": null, "error_weight_total": 7813, "error_weight_pvar": 29.310775, "logical_failure_rate": 0.51, "physical_error_rate": 0.23115384615384615, "wall_time": 1708.1004603514448}, {"code": "Color 6.6.6 15", "n_k_d": [169, 1, 15], "time_steps": 1, "error_model": "Biased-depolarizing (bias=1, axis='Z')", "decoder": "Color 6.6.6 MPS (chi=36)", "error_probability": 0.24, "measurement_error_probability": 0.0, "n_run": 200, "n_success": 97, "n_fail": 103, "n_logical_commutations": [67, 65], "custom_totals": null, "error_weight_total": 8159, "error_weight_pvar": 26.182975, "logical_failure_rate": 0.515, "physical_error_rate": 0.2413905325443787, "wall_time": 1716.9099422097206}]