[{"code": "Color 6.6.6 9", "n_k_d": [61, 1, 9], "time_steps": 1, "error_model": "Biased-depolarizing (bias=80, axis='Z')", "decoder": "Color 6.6.6 MPS (chi=36)", "error_probability": 0.37, "measurement_error_probability": 0.0, "n_run": 200, "n_success": 144, "n_fail": 56, "n_logical_commutations": [47, 10], "custom_totals": null, "error_weight_total": 4435, "error_weight_pvar": 14.734375, "logical_failure_rate": 0.28, "physical_error_rate": 0.3635245901639344, "wall_time": 132.230667992495}, {"code": "Color 6.6.6 9", "n_k_d": [61, 1, 9], "time_steps": 1, "error_model": "Biased-depolarizing (bias=80, axis='Z')", "decoder": "Color 6.6.6 MPS (chi=36)", "error_probability": 0.3811111111111111, "measurement_error_probability": 0.0, "n_run": 200, "n_success": 137, "n_fail": 63, "n_logical_commutations": [56, 11], "custom_totals": null, "error_weight_total": 4602, "error_weight_pvar": 14.1299, "logical_failure_rate": 0.315, "physical_error_rate": 0.37721311475409836, "wall_time": 132.20836980454624}, {"code": "Color 6.6.6 9", "n_k_d": [61, 1, 9], "time_steps": 1, "error_model": "Biased-depolarizing (bias=80, axis='Z')", "decoder": "Color 6.6.6 MPS (chi=36)", "error_probability": 0.3922222222222222, "measurement_error_probability": 0.0, "n_run": 200, "n_success": 138, "n_fail": 62, "n_logical_commutations": [55, 8], "custom_totals": null, "error_weight_total": 4717, "error_weight_pvar": 13.852775, "logical_failure_rate": 0.31, "physical_error_rate": 0.38663934426229507, "wall_time": 131.60124513227493}, {"code": "Color 6.6.6 9", "n_k_d": [61, 1, 9], "time_steps": 1, "error_model": "Biased-depolarizing (bias=80, axis='Z')", "decoder": "Color 6.6.6 MPS (chi=36)", "error_probability": 0.4033333333333333, "measurement_error_probability": 0.0, "n_run": 200, "n_success": 137, "n_fail": 63, "n_logical_commutations": [57, 8], "custom_totals": null, "error_weight_total": 4935, "error_weight_pvar": 14.929375, "logical_failure_rate": 0.315, "physical_error_rate": 0.40450819672131144, "wall_time": 132.19122685212642}, {"code": "Color 6.6.6 9", "n_k_d": [61, 1, 9], "time_steps": 1, "error_model": "Biased-depolarizing (bias=80, axis='Z')", "decoder": "Color 6.6.6 MPS (chi=36)", "error_probability": 0.41444444444444445, "measurement_error_probability": 0.0, "n_run": 200, "n_success": 125, "n_fail": 75, "n_logical_commutations": [69, 12], "custom_totals": null, "error_weight_total": 5102, "error_weight_pvar": 13.8399, "logical_failure_rate": 0.375, "physical_error_rate": 0.4181967213114754, "wall_time": 136.56799824163318}, {"code": "Color 6.6.6 9", "n_k_d": [61, 1, 9], "time_steps": 1, "error_model": "Biased-depolarizing (bias=80, axis='Z')", "decoder": "Color 6.6.6 MPS (chi=36)", "error_probability": 0.4255555555555555, "measurement_error_probability": 0.0, "n_run": 200, "n_success": 137, "n_fail": 63, "n_logical_commutations": [59, 5], "custom_totals": null, "error_weight_total": 5239, "error_weight_pvar": 14.816975, "logical_failure_rate": 0.315, "physical_error_rate": 0.42942622950819676, "wall_time": 136.15015200618654}, {"code": "Color 6.6.6 9", "n_k_d": [61, 1, 9], "time_steps": 1, "error_model": "Biased-depolarizing (bias=80, axis='Z')", "decoder": "Color 6.6.6 MPS (chi=36)", "error_probability": 0.43666666666666665, "measurement_error_probability": 0.0, "n_run": 200, "n_success": 128, "n_fail": 72, "n_logical_commutations": [65, 7], "custom_totals": null, "error_weight_total": 5332, "error_weight_pvar": 13.9744, "logical_failure_rate": 0.36, "physical_error_rate": 0.4370491803278689, "wall_time": 132.35078826732934}, {"code": "Color 6.6.6 9", "n_k_d": [61, 1, 9], "time_steps": 1, "error_model": "Biased-depolarizing (bias=80, axis='Z')", "decoder": "Color 6.6.6 MPS (chi=36)", "error_probability": 0.4477777777777777, "measurement_error_probability": 0.0, "n_run": 200, "n_success": 113, "n_fail": 87, "n_logical_commutations": [78, 12], "custom_totals": null, "error_weight_total": 5519, "error_weight_pvar": 12.800975, "logical_failure_rate": 0.435, "physical_error_rate": 0.4523770491803279, "wall_time": 132.43129331991076}, {"code": "Color 6.6.6 9", "n_k_d": [61, 1, 9], "time_steps": 1, "error_model": "Biased-depolarizing (bias=80, axis='Z')", "decoder": "Color 6.6.6 MPS (chi=36)", "error_probability": 0.45888888888888885, "measurement_error_probability": 0.0, "n_run": 200, "n_success": 130, "n_fail": 70, "n_logical_commutations": [66, 8], "custom_totals": null, "error_weight_total": 5582, "error_weight_pvar": 15.8419, "logical_failure_rate": 0.35, "physical_error_rate": 0.45754098360655737, "wall_time": 131.86886017024517}, {"code": "Color 6.6.6 9", "n_k_d": [61, 1, 9], "time_steps": 1, "error_model": "Biased-depolarizing (bias=80, axis='Z')", "decoder": "Color 6.6.6 MPS (chi=36)", "error_probability": 0.47, "measurement_error_probability": 0.0, "n_run": 200, "n_success": 107, "n_fail": 93, "n_logical_commutations": [88, 6], "custom_totals": null, "error_weight_total": 5681, "error_weight_pvar": 13.440975, "logical_failure_rate": 0.465, "physical_error_rate": 0.465655737704918, "wall_time": 131.7762928623706}, {"code": "Color 6.6.6 11", "n_k_d": [91, 1, 11], "time_steps": 1, "error_model": "Biased-depolarizing (bias=80, axis='Z')", "decoder": "Color 6.6.6 MPS (chi=36)", "error_probability": 0.37, "measurement_error_probability": 0.0, "n_run": 200, "n_success": 148, "n_fail": 52, "n_logical_commutations": [5, 47], "custom_totals": null, "error_weight_total": 6832, "error_weight_pvar": 21.3344, "logical_failure_rate": 0.26, "physical_error_rate": 0.3753846153846154, "wall_time": 440.1791646424681}, {"code": "Color 6.6.6 11", "n_k_d": [91, 1, 11], "time_steps": 1, "error_model": "Biased-depolarizing (bias=80, axis='Z')", "decoder": "Color 6.6.6 MPS (chi=36)", "error_probability": 0.3811111111111111, "measurement_error_probability": 0.0, "n_run": 200, "n_success": 154, "n_fail": 46, "n_logical_commutations": [12, 38], "custom_totals": null, "error_weight_total": 6928, "error_weight_pvar": 20.8704, "logical_failure_rate": 0.23, "physical_error_rate": 0.38065934065934065, "wall_time": 443.17192327976227}, {"code": "Color 6.6.6 11", "n_k_d": [91, 1, 11], "time_steps": 1, "error_model": "Biased-depolarizing (bias=80, axis='Z')", "decoder": "Color 6.6.6 MPS (chi=36)", "error_probability": 0.3922222222222222, "measurement_error_probability": 0.0, "n_run": 200, "n_success": 128, "n_fail": 72, "n_logical_commutations": [15, 62], "custom_totals": null, "error_weight_total": 7247, "error_weight_pvar": 22.269775, "logical_failure_rate": 0.36, "physical_error_rate": 0.3981868131868132, "wall_time": 441.70930506195873}, {"code": "Color 6.6.6 11", "n_k_d": [91, 1, 11], "time_steps": 1, "error_model": "Biased-depolarizing (bias=80, axis='Z')", "decoder": "Color 6.6.6 MPS (chi=36)", "error_probability": 0.4033333333333333, "measurement_error_probability": 0.0, "n_run": 200, "n_success": 142, "n_fail": 58, "n_logical_commutations": [12, 51], "custom_totals": null, "error_weight_total": 7418, "error_weight_pvar": 19.1219, "logical_failure_rate": 0.29, "physical_error_rate": 0.4075824175824176, "wall_time": 441.99027871061116}, {"code": "Color 6.6.6 11", "n_k_d": [91, 1, 11], "time_steps": 1, "error_model": "Biased-depolarizing (bias=80, axis='Z')", "decoder": "Color 6.6.6 MPS (chi=36)", "error_probability": 0.41444444444444445, "measurement_error_probability": 0.0, "n_run": 200, "n_success": 119, "n_fail": 81, "n_logical_commutations": [12, 71], "custom_totals": null, "error_weight_total": 7589, "error_weight_pvar": 22.981975, "logical_failure_rate": 0.405, "physical_error_rate": 0.416978021978022, "wall_time": 448.55791512224823}, {"code": "Color 6.6.6 11", "n_k_d": [91, 1, 11], "time_steps": 1, "error_model": "Biased-depolarizing (bias=80, axis='Z')", "decoder": "Color 6.6.6 MPS (chi=36)", "error_probability": 0.4255555555555555, "measurement_error_probability": 0.0, "n_run": 200, "n_success": 121, "n_fail": 79, "n_logical_commutations": [16, 67], "custom_totals": null, "error_weight_total": 7757, "error_weight_pvar": 26.518775, "logical_failure_rate": 0.395, "physical_error_rate": 0.42620879120879124, "wall_time": 441.2768195653334}, {"code": "Color 6.6.6 11", "n_k_d": [91, 1, 11], "time_steps": 1, "error_model": "Biased-depolarizing (bias=80, axis='Z')", "decoder": "Color 6.6.6 MPS (chi=36)", "error_probability": 0.43666666666666665, "measurement_error_probability": 0.0, "n_run": 200, "n_success": 124, "n_fail": 76, "n_logical_commutations": [13, 69], "custom_totals": null, "error_weight_total": 7854, "error_weight_pvar": 21.4571, "logical_failure_rate": 0.38, "physical_error_rate": 0.43153846153846154, "wall_time": 441.06465213932097}, {"code": "Color 6.6.6 11", "n_k_d": [91, 1, 11], "time_steps": 1, "error_model": "Biased-depolarizing (bias=80, axis='Z')", "decoder": "Color 6.6.6 MPS (chi=36)", "error_probability": 0.4477777777777777, "measurement_error_probability": 0.0, "n_run": 200, "n_success": 98, "n_fail": 102, "n_logical_commutations": [19, 86], "custom_totals": null, "error_weight_total": 8062, "error_weight_pvar": 23.3339, "logical_failure_rate": 0.51, "physical_error_rate": 0.442967032967033, "wall_time": 440.76029560901225}, {"code": "Color 6.6.6 11", "n_k_d": [91, 1, 11], "time_steps": 1, "error_model": "Biased-depolarizing (bias=80, axis='Z')", "decoder": "Color 6.6.6 MPS (chi=36)", "error_probability": 0.45888888888888885, "measurement_error_probability": 0.0, "n_run": 200, "n_success": 119, "n_fail": 81, "n_logical_commutations": [14, 75], "custom_totals": null, "error_weight_total": 8399, "error_weight_pvar": 21.724975, "logical_failure_rate": 0.405, "physical_error_rate": 0.4614835164835165, "wall_time": 446.90308617800474}, {"code": "Color 6.6.6 11", "n_k_d": [91, 1, 11], "time_steps": 1, "error_model": "Biased-depolarizing (bias=80, axis='Z')", "decoder": "Color 6.6.6 MPS (chi=36)", "error_probability": 0.47, "measurement_error_probability": 0.0, "n_run": 200, "n_success": 109, "n_fail": 91, "n_logical_commutations": [12, 82], "custom_totals": null, "error_weight_total": 8408, "error_weight_pvar": 22.9784, "logical_failure_rate": 0.455, "physical_error_rate": 0.46197802197802196, "wall_time": 443.34928734693676}, {"code": "Color 6.6.6 13", "n_k_d": [127, 1, 13], "time_steps": 1, "error_model": "Biased-depolarizing (bias=80, axis='Z')", "decoder": "Color 6.6.6 MPS (chi=36)", "error_probability": 0.37, "measurement_error_probability": 0.0, "n_run": 200, "n_success": 148, "n_fail": 52, "n_logical_commutations": [41, 15], "custom_totals": null, "error_weight_total": 9284, "error_weight_pvar": 26.6236, "logical_failure_rate": 0.26, "physical_error_rate": 0.36551181102362207, "wall_time": 952.9159494265914}, {"code": "Color 6.6.6 13", "n_k_d": [127, 1, 13], "time_steps": 1, "error_model": "Biased-depolarizing (bias=80, axis='Z')", "decoder": "Color 6.6.6 MPS (chi=36)", "error_probability": 0.3811111111111111, "measurement_error_probability": 0.0, "n_run": 200, "n_success": 155, "n_fail": 45, "n_logical_commutations": [36, 11], "custom_totals": null, "error_weight_total": 9583, "error_weight_pvar": 33.237775, "logical_failure_rate": 0.225, "physical_error_rate": 0.3772834645669291, "wall_time": 952.0261393785477}, {"code": "Color 6.6.6 13", "n_k_d": [127, 1, 13], "time_steps": 1, "error_model": "Biased-depolarizing (bias=80, axis='Z')", "decoder": "Color 6.6.6 MPS (chi=36)", "error_probability": 0.3922222222222222, "measurement_error_probability": 0.0, "n_run": 200, "n_success": 143, "n_fail": 57, "n_logical_commutations": [48, 11], "custom_totals": null, "error_weight_total": 9930, "error_weight_pvar": 30.6675, "logical_failure_rate": 0.285, "physical_error_rate": 0.3909448818897638, "wall_time": 955.6904018977657}, {"code": "Color 6.6.6 13", "n_k_d": [127, 1, 13], "time_steps": 1, "error_model": "Biased-depolarizing (bias=80, axis='Z')", "decoder": "Color 6.6.6 MPS (chi=36)", "error_probability": 0.4033333333333333, "measurement_error_probability": 0.0, "n_run": 200, "n_success": 142, "n_fail": 58, "n_logical_commutations": [47, 11], "custom_totals": null, "error_weight_total": 10166, "error_weight_pvar": 26.3811, "logical_failure_rate": 0.29, "physical_error_rate": 0.40023622047244095, "wall_time": 949.7933467784896}, {"code": "Color 6.6.6 13", "n_k_d": [127, 1, 13], "time_steps": 1, "error_model": "Biased-depolarizing (bias=80, axis='Z')", "decoder": "Color 6.6.6 MPS (chi=36)", "error_probability": 0.41444444444444445, "measurement_error_probability": 0.0, "n_run": 200, "n_success": 132, "n_fail": 68, "n_logical_commutations": [61, 11], "custom_totals": null, "error_weight_total": 10543, "error_weight_pvar": 30.663775, "logical_failure_rate": 0.34, "physical_error_rate": 0.4150787401574803, "wall_time": 962.4219054402784}, {"code": "Color 6.6.6 13", "n_k_d": [127, 1, 13], "time_steps": 1, "error_model": "Biased-depolarizing (bias=80, axis='Z')", "decoder": "Color 6.6.6 MPS (chi=36)", "error_probability": 0.4255555555555555, "measurement_error_probability": 0.0, "n_run": 200, "n_success": 128, "n_fail": 72, "n_logical_commutations": [59, 16], "custom_totals": null, "error_weight_total": 10895, "error_weight_pvar": 35.959375, "logical_failure_rate": 0.36, "physical_error_rate": 0.4289370078740158, "wall_time": 956.4182704016566}, {"code": "Color 6.6.6 13", "n_k_d": [127, 1, 13], "time_steps": 1, "error_model": "Biased-depolarizing (bias=80, axis='Z')", "decoder": "Color 6.6.6 MPS (chi=36)", "error_probability": 0.43666666666666665, "measurement_error_probability": 0.0, "n_run": 200, "n_success": 119, "n_fail": 81, "n_logical_commutations": [72, 13], "custom_totals": null, "error_weight_total": 11114, "error_weight_pvar": 34.3851, "logical_failure_rate": 0.405, "physical_error_rate": 0.4375590551181102, "wall_time": 947.5975728295743}, {"code": "Color 6.6.6 13", "n_k_d": [127, 1, 13], "time_steps": 1, "error_model": "Biased-depolarizing (bias=80, axis='Z')", "decoder": "Color 6.6.6 MPS (chi=36)", "error_probability": 0.4477777777777777, "measurement_error_probability": 0.0, "n_run": 200, "n_success": 102, "n_fail": 98, "n_logical_commutations": [85, 16], "custom_totals": null, "error_weight_total": 11489, "error_weight_pvar": 35.286975, "logical_failure_rate": 0.49, "physical_error_rate": 0.45232283464566925, "wall_time": 947.3801484303549}, {"code": "Color 6.6.6 13", "n_k_d": [127, 1, 13], "time_steps": 1, "error_model": "Biased-depolarizing (bias=80, axis='Z')", "decoder": "Color 6.6.6 MPS (chi=36)", "error_probability": 0.45888888888888885, "measurement_error_probability": 0.0, "n_run": 200, "n_success": 107, "n_fail": 93, "n_logical_commutations": [82, 15], "custom_totals": null, "error_weight_total": 11577, "error_weight_pvar": 26.181775, "logical_failure_rate": 0.465, "physical_error_rate": 0.4557874015748032, "wall_time": 946.543056095019}, {"code": "Color 6.6.6 13", "n_k_d": [127, 1, 13], "time_steps": 1, "error_model": "Biased-depolarizing (bias=80, axis='Z')", "decoder": "Color 6.6.6 MPS (chi=36)", "error_probability": 0.47, "measurement_error_probability": 0.0, "n_run": 200, "n_success": 110, "n_fail": 90, "n_logical_commutations": [78, 15], "custom_totals": null, "error_weight_total": 11891, "error_weight_pvar": 30.037975, "logical_failure_rate": 0.45, "physical_error_rate": 0.4681496062992126, "wall_time": 958.0138605814427}, {"code": "Color 6.6.6 15", "n_k_d": [169, 1, 15], "time_steps": 1, "error_model": "Biased-depolarizing (bias=80, axis='Z')", "decoder": "Color 6.6.6 MPS (chi=36)", "error_probability": 0.37, "measurement_error_probability": 0.0, "n_run": 200, "n_success": 164, "n_fail": 36, "n_logical_commutations": [11, 25], "custom_totals": null, "error_weight_total": 12320, "error_weight_pvar": 37.7, "logical_failure_rate": 0.18, "physical_error_rate": 0.3644970414201183, "wall_time": 1657.2606739979237}, {"code": "Color 6.6.6 15", "n_k_d": [169, 1, 15], "time_steps": 1, "error_model": "Biased-depolarizing (bias=80, axis='Z')", "decoder": "Color 6.6.6 MPS (chi=36)", "error_probability": 0.3811111111111111, "measurement_error_probability": 0.0, "n_run": 200, "n_success": 152, "n_fail": 48, "n_logical_commutations": [12, 39], "custom_totals": null, "error_weight_total": 12974, "error_weight_pvar": 46.9331, "logical_failure_rate": 0.24, "physical_error_rate": 0.3838461538461539, "wall_time": 1656.135532796383}, {"code": "Color 6.6.6 15", "n_k_d": [169, 1, 15], "time_steps": 1, "error_model": "Biased-depolarizing (bias=80, axis='Z')", "decoder": "Color 6.6.6 MPS (chi=36)", "error_probability": 0.3922222222222222, "measurement_error_probability": 0.0, "n_run": 200, "n_success": 134, "n_fail": 66, "n_logical_commutations": [10, 60], "custom_totals": null, "error_weight_total": 13280, "error_weight_pvar": 41.96, "logical_failure_rate": 0.33, "physical_error_rate": 0.39289940828402364, "wall_time": 1664.7417202321813}, {"code": "Color 6.6.6 15", "n_k_d": [169, 1, 15], "time_steps": 1, "error_model": "Biased-depolarizing (bias=80, axis='Z')", "decoder": "Color 6.6.6 MPS (chi=36)", "error_probability": 0.4033333333333333, "measurement_error_probability": 0.0, "n_run": 200, "n_success": 139, "n_fail": 61, "n_logical_commutations": [9, 53], "custom_totals": null, "error_weight_total": 13557, "error_weight_pvar": 37.738775, "logical_failure_rate": 0.305, "physical_error_rate": 0.401094674556213, "wall_time": 1661.148961241357}, {"code": "Color 6.6.6 15", "n_k_d": [169, 1, 15], "time_steps": 1, "error_model": "Biased-depolarizing (bias=80, axis='Z')", "decoder": "Color 6.6.6 MPS (chi=36)", "error_probability": 0.41444444444444445, "measurement_error_probability": 0.0, "n_run": 200, "n_success": 131, "n_fail": 69, "n_logical_commutations": [17, 57], "custom_totals": null, "error_weight_total": 13997, "error_weight_pvar": 39.164775, "logical_failure_rate": 0.345, "physical_error_rate": 0.41411242603550297, "wall_time": 1674.7784047378227}, {"code": "Color 6.6.6 15", "n_k_d": [169, 1, 15], "time_steps": 1, "error_model": "Biased-depolarizing (bias=80, axis='Z')", "decoder": "Color 6.6.6 MPS (chi=36)", "error_probability": 0.4255555555555555, "measurement_error_probability": 0.0, "n_run": 200, "n_success": 129, "n_fail": 71, "n_logical_commutations": [15, 62], "custom_totals": null, "error_weight_total": 14436, "error_weight_pvar": 42.9176, "logical_failure_rate": 0.355, "physical_error_rate": 0.42710059171597636, "wall_time": 1661.7325771478936}, {"code": "Color 6.6.6 15", "n_k_d": [169, 1, 15], "time_steps": 1, "error_model": "Biased-depolarizing (bias=80, axis='Z')", "decoder": "Color 6.6.6 MPS (chi=36)", "error_probability": 0.43666666666666665, "measurement_error_probability": 0.0, "n_run": 200, "n_success": 121, "n_fail": 79, "n_logical_commutations": [14, 71], "custom_totals": null, "error_weight_total": 14793, "error_weight_pvar": 41.593775, "logical_failure_rate": 0.395, "physical_error_rate": 0.4376627218934911, "wall_time": 1663.1308445390314}, {"code": "Color 6.6.6 15", "n_k_d": [169, 1, 15], "time_steps": 1, "error_model": "Biased-depolarizing (bias=80, axis='Z')", "decoder": "Color 6.6.6 MPS (chi=36)", "error_probability": 0.4477777777777777, "measurement_error_probability": 0.0, "n_run": 200, "n_success": 119, "n_fail": 81, "n_logical_commutations": [12, 76], "custom_totals": null, "error_weight_total": 15246, "error_weight_pvar": 43.1071, "logical_failure_rate": 0.405, "physical_error_rate": 0.4510650887573964, "wall_time": 1664.7734252763912}, {"code": "Color 6.6.6 15", "n_k_d": [169, 1, 15], "time_steps": 1, "error_model": "Biased-depolarizing (bias=80, axis='Z')", "decoder": "Color 6.6.6 MPS (chi=36)", "error_probability": 0.45888888888888885, "measurement_error_probability": 0.0, "n_run": 200, "n_success": 119, "n_fail": 81, "n_logical_commutations": [10, 75], "custom_totals": null, "error_weight_total": 15357, "error_weight_pvar": 50.638775, "logical_failure_rate": 0.405, "physical_error_rate": 0.4543491124260355, "wall_time": 1653.4095555180684}, {"code": "Color 6.6.6 15", "n_k_d": [169, 1, 15], "time_steps": 1, "error_model": "Biased-depolarizing (bias=80, axis='Z')", "decoder": "Color 6.6.6 MPS (chi=36)", "error_probability": 0.47, "measurement_error_probability": 0.0, "n_run": 200, "n_success": 97, "n_fail": 103, "n_logical_commutations": [16, 96], "custom_totals": null, "error_weight_total": 16158, "error_weight_pvar": 37.1959, "logical_failure_rate": 0.515, "physical_error_rate": 0.4780473372781065, "wall_time": 1656.3498374465853}]